{
   "generated_by" : "Author",
   "dynamic_config" : 1,
   "name" : "Tie-Hash-DBD",
   "author" : [
      "H.Merijn Brand <h.m.brand@xs4all.nl>"
   ],
   "meta-spec" : {
      "version" : "2",
      "url" : "http://search.cpan.org/perldoc?CPAN::Meta::Spec"
   },
   "abstract" : "Tie plain hashes to DBI interface",
   "license" : [
      "perl_5"
   ],
   "provides" : {
      "Tie::Array::DBD" : {
         "version" : "0.13",
         "file" : "lib/Tie/Array/DBD.pm"
      },
      "Tie::Hash::DBD" : {
         "file" : "lib/Tie/Hash/DBD.pm",
         "version" : "0.13"
      }
   },
   "version" : "0.13",
   "prereqs" : {
      "configure" : {
         "requires" : {
            "ExtUtils::MakeMaker" : "0"
         }
      },
      "runtime" : {
         "requires" : {
            "DBI" : "1.613",
            "Storable" : "0",
            "Carp" : "0",
            "perl" : "5.008003"
         },
         "recommends" : {
            "DBD::SQLite" : "1.42",
            "DBI" : "1.631",
            "perl" : "5.018002"
         }
      },
      "test" : {
         "requires" : {
            "Test::More" : "0.90",
            "Time::HiRes" : "0",
            "Test::Harness" : "0"
         },
         "recommends" : {
            "Test::More" : "1.001003"
         }
      }
   },
   "release_status" : "stable",
   "resources" : {
      "license" : [
         "http://dev.perl.org/licenses/"
      ],
      "repository" : {
         "web" : "http://repo.or.cz/w/Tie-Hash-DBD.git",
         "type" : "git",
         "url" : "http://repo.or.cz/r/Tie-Hash-DBD.git"
      }
   }
}
